[{"Country":"Aruba","Code":"ABW","Value":1.2916430235,"Year":2017},{"Country":"Andorra","Code":"ADO","Value":1.2422145605,"Year":2017},{"Country":"Afghanistan","Code":"AFG","Value":-1.5173414946,"Year":2017},{"Country":"Angola","Code":"AGO","Value":-1.4124878645,"Year":2017},{"Country":"Anguilla","Code":"AIA","Value":1.2422145605,"Year":2017},{"Country":"Albania","Code":"ALB","Value":-0.4183090329,"Year":2017},{"Country":"Netherlands Antilles (former)","Code":"ANT","Value":null,"Year":2017},{"Country":"United Arab Emirates","Code":"ARE","Value":1.1336040497,"Year":2017},{"Country":"Argentina","Code":"ARG","Value":-0.2559460104,"Year":2017},{"Country":"Armenia","Code":"ARM","Value":-0.5604560971,"Year":2017},{"Country":"American Samoa","Code":"ASM","Value":1.8405307531,"Year":2017},{"Country":"Antigua and Barbuda","Code":"ATG","Value":0.2420828342,"Year":2017},{"Country":"Australia","Code":"AUS","Value":1.7950495481,"Year":2017},{"Country":"Austria","Code":"AUT","Value":1.5260113478,"Year":2017},{"Country":"Azerbaijan","Code":"AZE","Value":-0.8853458166,"Year":2017},{"Country":"Burundi","Code":"BDI","Value":-1.2838747501,"Year":2017},{"Country":"Belgium","Code":"BEL","Value":1.4971171618,"Year":2017},{"Country":"Benin","Code":"BEN","Value":-0.5541116595,"Year":2017},{"Country":"Burkina Faso","Code":"BFA","Value":-0.1137550101,"Year":2017},{"Country":"Bangladesh","Code":"BGD","Value":-0.8317309022,"Year":2017},{"Country":"Bulgaria","Code":"BGR","Value":-0.1611122638,"Year":2017},{"Country":"Bahrain","Code":"BHR","Value":-0.1409595758,"Year":2017},{"Country":"Bahamas, The","Code":"BHS","Value":1.1738185883,"Year":2017},{"Country":"Bosnia and Herzegovina","Code":"BIH","Value":-0.5154479742,"Year":2017},{"Country":"Belarus","Code":"BLR","Value":-0.2575778067,"Year":2017},{"Country":"Belize","Code":"BLZ","Value":-0.271979928,"Year":2017},{"Country":"Bermuda","Code":"BMU","Value":1.2422145605,"Year":2017},{"Country":"Bolivia","Code":"BOL","Value":-0.6573039293,"Year":2017},{"Country":"Brazil","Code":"BRA","Value":-0.5320730209,"Year":2017},{"Country":"Barbados","Code":"BRB","Value":1.4211093187,"Year":2017},{"Country":"Brunei Darussalam","Code":"BRN","Value":0.7126349807,"Year":2017},{"Country":"Bhutan","Code":"BTN","Value":1.5682936907,"Year":2017},{"Country":"South Sudan","Code":"SSD","Value":-1.7133142948,"Year":2017},{"Country":"Botswana","Code":"BWA","Value":0.7951008677,"Year":2017},{"Country":"Central African Republic","Code":"CAF","Value":-1.1732126474,"Year":2017},{"Country":"Canada","Code":"CAN","Value":1.9242578745,"Year":2017},{"Country":"Switzerland","Code":"CHE","Value":1.9890344143,"Year":2017},{"Country":"Chile","Code":"CHL","Value":1.0392905474,"Year":2017},{"Country":"China","Code":"CHN","Value":-0.2699364126,"Year":2017},{"Country":"C\u00f4te d'Ivoire","Code":"CIV","Value":-0.5253295898,"Year":2017},{"Country":"Cameroon","Code":"CMR","Value":-1.1993232965,"Year":2017},{"Country":"Congo, Rep.","Code":"COG","Value":-1.3306100368,"Year":2017},{"Country":"Cook Islands","Code":"COK","Value":null,"Year":2017},{"Country":"Colombia","Code":"COL","Value":-0.3700208366,"Year":2017},{"Country":"Comoros","Code":"COM","Value":-0.6849559546,"Year":2017},{"Country":"Cape Verde","Code":"CPV","Value":0.8347586393,"Year":2017},{"Country":"Costa Rica","Code":"CRI","Value":0.4666402042,"Year":2017},{"Country":"Cuba","Code":"CUB","Value":0.2656265497,"Year":2017},{"Country":"Cayman Islands","Code":"CYM","Value":0.5268431902,"Year":2017},{"Country":"Cyprus","Code":"CYP","Value":0.7827288508,"Year":2017},{"Country":"Czech Republic","Code":"CZE","Value":0.5676769614,"Year":2017},{"Country":"Germany","Code":"DEU","Value":1.8410892487,"Year":2017},{"Country":"Djibouti","Code":"DJI","Value":-0.6407171488,"Year":2017},{"Country":"Dominica","Code":"DMA","Value":0.6515269279,"Year":2017},{"Country":"Denmark","Code":"DNK","Value":2.1933786869,"Year":2017},{"Country":"Dominican Republic","Code":"DOM","Value":-0.7389132977,"Year":2017},{"Country":"Algeria","Code":"DZA","Value":-0.6041751504,"Year":2017},{"Country":"Ecuador","Code":"ECU","Value":-0.5996183753,"Year":2017},{"Country":"Egypt, Arab Rep.","Code":"EGY","Value":-0.5521880984,"Year":2017},{"Country":"Eritrea","Code":"ERI","Value":-1.2028697729,"Year":2017},{"Country":"Spain","Code":"ESP","Value":0.4917678833,"Year":2017},{"Country":"Estonia","Code":"EST","Value":1.2424126863,"Year":2017},{"Country":"Ethiopia","Code":"ETH","Value":-0.5574791431,"Year":2017},{"Country":"Finland","Code":"FIN","Value":2.2158105373,"Year":2017},{"Country":"Fiji","Code":"FJI","Value":0.3590476215,"Year":2017},{"Country":"France","Code":"FRA","Value":1.2594825029,"Year":2017},{"Country":"Micronesia, Fed. Sts.","Code":"FSM","Value":0.7492542267,"Year":2017},{"Country":"Gabon","Code":"GAB","Value":-0.816114068,"Year":2017},{"Country":"United Kingdom","Code":"GBR","Value":1.8433433771,"Year":2017},{"Country":"Georgia","Code":"GEO","Value":0.7445272207,"Year":2017},{"Country":"Ghana","Code":"GHA","Value":-0.2290350944,"Year":2017},{"Country":"Guinea","Code":"GIN","Value":-1.0111078024,"Year":2017},{"Country":"Gambia, The","Code":"GMB","Value":-0.6292392612,"Year":2017},{"Country":"Guinea-Bissau","Code":"GNB","Value":-1.5628253222,"Year":2017},{"Country":"Equatorial Guinea","Code":"GNQ","Value":-1.8263611794,"Year":2017},{"Country":"Greece","Code":"GRC","Value":-0.1383458972,"Year":2017},{"Country":"Grenada","Code":"GRD","Value":0.475343436,"Year":2017},{"Country":"Greenland","Code":"GRL","Value":1.182941556,"Year":2017},{"Country":"Guatemala","Code":"GTM","Value":-0.7398667932,"Year":2017},{"Country":"French Guiana","Code":"GUF","Value":0.9959359169,"Year":2017},{"Country":"Guam","Code":"GUM","Value":1.2422145605,"Year":2017},{"Country":"Guyana","Code":"GUY","Value":-0.5081118345,"Year":2017},{"Country":"Hong Kong SAR, China","Code":"HKG","Value":1.614928484,"Year":2017},{"Country":"Honduras","Code":"HND","Value":-0.7176982164,"Year":2017},{"Country":"Croatia","Code":"HRV","Value":0.1867005974,"Year":2017},{"Country":"Haiti","Code":"HTI","Value":-1.238203764,"Year":2017},{"Country":"Hungary","Code":"HUN","Value":0.0892914683,"Year":2017},{"Country":"Indonesia","Code":"IDN","Value":-0.2527087331,"Year":2017},{"Country":"India","Code":"IND","Value":-0.2398076504,"Year":2017},{"Country":"Ireland","Code":"IRL","Value":1.5485646725,"Year":2017},{"Country":"Iran, Islamic Rep.","Code":"IRN","Value":-0.8116927147,"Year":2017},{"Country":"Iraq","Code":"IRQ","Value":-1.3721330166,"Year":2017},{"Country":"Iceland","Code":"ISL","Value":1.8381211758,"Year":2017},{"Country":"Israel","Code":"ISR","Value":0.8267115355,"Year":2017},{"Country":"Italy","Code":"ITA","Value":0.1885997653,"Year":2017},{"Country":"Jamaica","Code":"JAM","Value":-0.1725083888,"Year":2017},{"Country":"Jordan","Code":"JOR","Value":0.2597678006,"Year":2017},{"Country":"Japan","Code":"JPN","Value":1.5224291086,"Year":2017},{"Country":"Kazakhstan","Code":"KAZ","Value":-0.8209888339,"Year":2017},{"Country":"Kenya","Code":"KEN","Value":-0.9537178874,"Year":2017},{"Country":"Kyrgyz Republic","Code":"KGZ","Value":-1.0540224314,"Year":2017},{"Country":"Cambodia","Code":"KHM","Value":-1.2913807631,"Year":2017},{"Country":"Kiribati","Code":"KIR","Value":0.3900577426,"Year":2017},{"Country":"St. Kitts and Nevis","Code":"KNA","Value":0.5075246096,"Year":2017},{"Country":"Korea, Rep.","Code":"KOR","Value":0.4808298349,"Year":2017},{"Country":"Kuwait","Code":"KWT","Value":-0.3315037191,"Year":2017},{"Country":"Lao PDR","Code":"LAO","Value":-0.9359312057,"Year":2017},{"Country":"Lebanon","Code":"LBN","Value":-1.0001802444,"Year":2017},{"Country":"Liberia","Code":"LBR","Value":-0.6628168225,"Year":2017},{"Country":"Libya","Code":"LBY","Value":-1.5915066004,"Year":2017},{"Country":"St. Lucia","Code":"LCA","Value":0.5868739486,"Year":2017},{"Country":"Liechtenstein","Code":"LIE","Value":2.0564427376,"Year":2017},{"Country":"Sri Lanka","Code":"LKA","Value":-0.4518554509,"Year":2017},{"Country":"Lesotho","Code":"LSO","Value":-0.0309465379,"Year":2017},{"Country":"Lithuania","Code":"LTU","Value":0.5537297726,"Year":2017},{"Country":"Luxembourg","Code":"LUX","Value":1.9854968786,"Year":2017},{"Country":"Latvia","Code":"LVA","Value":0.5358247757,"Year":2017},{"Country":"Kosovo","Code":"KSV","Value":-0.5039746165,"Year":2017},{"Country":"Macao SAR, China","Code":"MAC","Value":0.6420047879,"Year":2017},{"Country":"Morocco","Code":"MAR","Value":-0.1394774169,"Year":2017},{"Country":"Monaco","Code":"MCO","Value":null,"Year":2017},{"Country":"Moldova","Code":"MDA","Value":-0.7986267209,"Year":2017},{"Country":"Madagascar","Code":"MDG","Value":-1.0509544611,"Year":2017},{"Country":"Maldives","Code":"MDV","Value":-0.7875925303,"Year":2017},{"Country":"Mexico","Code":"MEX","Value":-0.9279869795,"Year":2017},{"Country":"Marshall Islands","Code":"MHL","Value":0.0015589696,"Year":2017},{"Country":"Macedonia, FYR","Code":"MKD","Value":-0.3072252572,"Year":2017},{"Country":"Mali","Code":"MLI","Value":-0.6403126121,"Year":2017},{"Country":"Malta","Code":"MLT","Value":0.7396525741,"Year":2017},{"Country":"Myanmar","Code":"MMR","Value":-0.5652627945,"Year":2017},{"Country":"Mongolia","Code":"MNG","Value":-0.4517063797,"Year":2017},{"Country":"Montenegro","Code":"MNE","Value":-0.0877144411,"Year":2017},{"Country":"Mozambique","Code":"MOZ","Value":-0.8348411918,"Year":2017},{"Country":"Mauritania","Code":"MRT","Value":-0.751313746,"Year":2017},{"Country":"Martinique","Code":"MTQ","Value":1.2422145605,"Year":2017},{"Country":"Mauritius","Code":"MUS","Value":0.2011648268,"Year":2017},{"Country":"Malawi","Code":"MWI","Value":-0.658003509,"Year":2017},{"Country":"Malaysia","Code":"MYS","Value":0.0257437453,"Year":2017},{"Country":"Namibia","Code":"NAM","Value":0.3206743002,"Year":2017},{"Country":"Niger","Code":"NER","Value":-0.6633669138,"Year":2017},{"Country":"Nigeria","Code":"NGA","Value":-1.0767480135,"Year":2017},{"Country":"Nicaragua","Code":"NIC","Value":-0.8722236156,"Year":2017},{"Country":"Niue","Code":"NIU","Value":null,"Year":2017},{"Country":"Netherlands","Code":"NLD","Value":1.8672780991,"Year":2017},{"Country":"Norway","Code":"NOR","Value":2.2367768288,"Year":2017},{"Country":"Nepal","Code":"NPL","Value":-0.7495683432,"Year":2017},{"Country":"Nauru","Code":"NRU","Value":-0.4729841948,"Year":2017},{"Country":"New Zealand","Code":"NZL","Value":2.2411146164,"Year":2017},{"Country":"Oman","Code":"OMN","Value":0.2476177812,"Year":2017},{"Country":"Pakistan","Code":"PAK","Value":-0.7782837152,"Year":2017},{"Country":"Panama","Code":"PAN","Value":-0.5397643447,"Year":2017},{"Country":"Palau","Code":"PLW","Value":-0.4729841948,"Year":2017},{"Country":"Peru","Code":"PER","Value":-0.4962631166,"Year":2017},{"Country":"Philippines","Code":"PHL","Value":-0.475569874,"Year":2017},{"Country":"Papua New Guinea","Code":"PNG","Value":-0.8989989161,"Year":2017},{"Country":"Poland","Code":"POL","Value":0.7249847651,"Year":2017},{"Country":"Puerto Rico","Code":"PRI","Value":0.1379475445,"Year":2017},{"Country":"Korea, Dem. Rep.","Code":"PRK","Value":-1.4811458588,"Year":2017},{"Country":"Portugal","Code":"PRT","Value":0.87394315,"Year":2017},{"Country":"Paraguay","Code":"PRY","Value":-0.7252022028,"Year":2017},{"Country":"Qatar","Code":"QAT","Value":0.7338908315,"Year":2017},{"Country":"R\u00e9union","Code":"REU","Value":0.6438982487,"Year":2017},{"Country":"Romania","Code":"ROM","Value":-0.0314775556,"Year":2017},{"Country":"Russian Federation","Code":"RUS","Value":-0.8923912644,"Year":2017},{"Country":"Rwanda","Code":"RWA","Value":0.6330296397,"Year":2017},{"Country":"Samoa","Code":"WSM","Value":0.6594558954,"Year":2017},{"Country":"Saudi Arabia","Code":"SAU","Value":0.363823235,"Year":2017},{"Country":"Sudan","Code":"SDN","Value":-1.5319639444,"Year":2017},{"Country":"Senegal","Code":"SEN","Value":-0.0891060978,"Year":2017},{"Country":"Singapore","Code":"SGP","Value":2.1335821152,"Year":2017},{"Country":"Solomon Islands","Code":"SLB","Value":0.1115307659,"Year":2017},{"Country":"Sierra Leone","Code":"SLE","Value":-0.5661565065,"Year":2017},{"Country":"El Salvador","Code":"SLV","Value":-0.5067081451,"Year":2017},{"Country":"San Marino","Code":"SMR","Value":null,"Year":2017},{"Country":"Somalia","Code":"SOM","Value":-1.7163375616,"Year":2017},{"Country":"S\u00e3o Tom\u00e9 and Principe","Code":"STP","Value":0.1712367684,"Year":2017},{"Country":"Suriname","Code":"SUR","Value":-0.1743334532,"Year":2017},{"Country":"Slovak Republic","Code":"SVK","Value":0.223769635,"Year":2017},{"Country":"Slovenia","Code":"SVN","Value":0.8137993217,"Year":2017},{"Country":"Sweden","Code":"SWE","Value":2.1389346123,"Year":2017},{"Country":"Swaziland","Code":"SWZ","Value":-0.271371156,"Year":2017},{"Country":"Seychelles","Code":"SYC","Value":0.6810741425,"Year":2017},{"Country":"Syrian Arab Republic","Code":"SYR","Value":-1.5629940033,"Year":2017},{"Country":"Chad","Code":"TCD","Value":-1.432356596,"Year":2017},{"Country":"Togo","Code":"TGO","Value":-0.7109718323,"Year":2017},{"Country":"Thailand","Code":"THA","Value":-0.3858818412,"Year":2017},{"Country":"Tajikistan","Code":"TJK","Value":-1.3310505152,"Year":2017},{"Country":"Turkmenistan","Code":"TKM","Value":-1.4823240042,"Year":2017},{"Country":"Timor-Leste","Code":"TMP","Value":-0.5402248502,"Year":2017},{"Country":"Tonga","Code":"TON","Value":-0.1609317362,"Year":2017},{"Country":"Trinidad and Tobago","Code":"TTO","Value":-0.3645433486,"Year":2017},{"Country":"Tunisia","Code":"TUN","Value":-0.108641766,"Year":2017},{"Country":"Turkey","Code":"TUR","Value":-0.19324103,"Year":2017},{"Country":"Tuvalu","Code":"TUV","Value":0.0616561249,"Year":2017},{"Country":"Taiwan, China","Code":"TWN","Value":0.9647804499,"Year":2017},{"Country":"Tanzania","Code":"TZA","Value":-0.4630896747,"Year":2017},{"Country":"Uganda","Code":"UGA","Value":-1.0423154831,"Year":2017},{"Country":"Ukraine","Code":"UKR","Value":-0.783946991,"Year":2017},{"Country":"Uruguay","Code":"URY","Value":1.2927091122,"Year":2017},{"Country":"United States","Code":"USA","Value":1.3812417984,"Year":2017},{"Country":"Uzbekistan","Code":"UZB","Value":-1.1592868567,"Year":2017},{"Country":"St. Vincent and the Grenadines","Code":"VCT","Value":0.7241975665,"Year":2017},{"Country":"Venezuela, RB","Code":"VEN","Value":-1.3640570641,"Year":2017},{"Country":"Virgin Islands (U.S.)","Code":"VIR","Value":0.6438982487,"Year":2017},{"Country":"Vietnam","Code":"VNM","Value":-0.5831350088,"Year":2017},{"Country":"Vanuatu","Code":"VUT","Value":0.0057819174,"Year":2017},{"Country":"West Bank and Gaza","Code":"WBG","Value":-0.0280455165,"Year":2017},{"Country":"Jersey, Channel Islands","Code":"JEY","Value":1.1662735939,"Year":2017},{"Country":"Yemen, Rep.","Code":"YEM","Value":-1.5927855968,"Year":2017},{"Country":"Serbia","Code":"SRB","Value":-0.3751128614,"Year":2017},{"Country":"South Africa","Code":"ZAF","Value":-0.0218271278,"Year":2017},{"Country":"Congo, Dem. Rep.","Code":"ZAR","Value":-1.4181195498,"Year":2017},{"Country":"Zambia","Code":"ZMB","Value":-0.5422127843,"Year":2017},{"Country":"Zimbabwe","Code":"ZWE","Value":-1.2735836506,"Year":2017}]